{
  "dataBindings": [
    {
      "attr": "primaryColor",
      "valueType": "Color"
    },
    {
      "attr": "secondaryColor",
      "valueType": "Color"
    }
  ],
  "width": 48,
  "height": 48,
  "comps": [
    {
      "type": "shape",
      "background": {
        "func": "attr@primaryColor",
        "value": "#ffb400"
      },
      "points": [
        16,
        32,
        19,
        35,
        37,
        17,
        34,
        14,
        16,
        32
      ]
    },
    {
      "type": "shape",
      "background": {
        "func": "attr@secondaryColor",
        "value": "#070c2b"
      },
      "points": [
        22,
        32,
        19,
        35,
        11,
        27,
        14,
        24,
        22,
        32
      ]
    }
  ]
}