{
  "dataBindings": [
    {
      "attr": "primaryColor",
      "valueType": "Color"
    },
    {
      "attr": "secondaryColor",
      "valueType": "Color"
    }
  ],
  "width": 48,
  "height": 48,
  "comps": [
    {
      "type": "shape",
      "background": {
        "func": "attr@primaryColor",
        "value": "#ffb400"
      },
      "points": [
        37,
        22,
        34,
        19,
        34,
        41,
        14,
        41,
        14,
        19,
        11,
        22,
        6,
        17,
        14.952,
        7,
        33.052,
        7,
        42,
        17,
        37,
        22
      ]
    },
    {
      "type": "shape",
      "background": {
        "func": "attr@secondaryColor",
        "value": "#070c2b"
      },
      "points": [
        18,
        7,
        30,
        7,
        29.88471,
        8.17054,
        29.54328,
        9.2961,
        28.98882,
        10.33342,
        28.24264,
        11.24264,
        27.33342,
        11.98882,
        26.2961,
        12.54328,
        25.17054,
        12.88471,
        24,
        13,
        22.82946,
        12.88471,
        21.7039,
        12.54328,
        20.66658,
        11.98882,
        19.75736,
        11.24264,
        19.01118,
        10.33342,
        18.45672,
        9.2961,
        18.11529,
        8.17054,
        18,
        7,
        18,
        7,
        14,
        39,
        34,
        39,
        34,
        41,
        14,
        41,
        14,
        39,
        14,
        39
      ],
      "segments": [
        1,
        2,
        2,
        2,
        2,
        2,
        2,
        2,
        2,
        2,
        2,
        2,
        2,
        2,
        2,
        2,
        2,
        2,
        2,
        1,
        2,
        2,
        2,
        2,
        2
      ]
    }
  ]
}