{
  "modified": "Wed Nov 21 2018 16:28:53 GMT+0800 (中国标准时间)",
  "dataBindings": [
    {
      "attr": "color1",
      "valueType": "Color",
      "defaultValue": "rgb(1,100,143)"
    },
    {
      "attr": "color2",
      "valueType": "Color",
      "defaultValue": "#60ACFC"
    },
    {
      "attr": "barData",
      "valueType": "NumberArray",
      "defaultValue": [
        1,
        2,
        3
      ]
    }
  ],
  "renderHTML": "__ht__function(data, gv, cache) {\n\n    var option = {\n        tooltip: {\n            show: true\n        },\n        xAxis: {\n            type: 'category',\n            data: ['高炉', '平均', '最佳'],\n            axisLabel: {\n                color: 'rgb(255,255,255)'\n            },\n            axisTick: {show: false},\n            axisLine: {\n                lineStyle: {color: 'rgba(255,255,255,0.3)'}\n            },\n            splitLine: {\n                lineStyle: {color: 'rgba(255,255,255,0.3)'}\n            }\n        },\n        yAxis: {\n            type: 'value',\n            axisLabel: {\n                color: 'rgb(255,255,255)'\n            },\n            axisTick: {show: false},\n            axisLine: {\n                lineStyle: {color: 'rgba(255,255,255,0.3)'}\n            },\n            splitLine: {\n                lineStyle: {color: 'rgba(255,255,255,0.3)'}\n            }\n        },\n        series: [{\n            barCategoryGap:'50%',\n            data: [120, 200, 150],\n            type: 'bar',\n            itemStyle: {\n                normal: {\n                    color: new echarts.graphic.LinearGradient(\n                        0, 0, 1, 1,\n                        [\n                            {offset: 0, color: '#60ACFC'},\n                            {offset: 1, color: 'rgb(1,100,143)'}\n                        ]\n                    )\n                },\n            }\n        }]\n    };\n\n    if (!cache.htmlView) {\n        cache.htmlView = document.createElement('div');\n        cache.htmlView.style.position = 'absolute';\n        cache.htmlChart = echarts.init(cache.htmlView);\n\n        // layoutHTML will be called when the data needs to be drawing\n        cache.htmlView.layoutHTML = function () {\n            gv.layoutHTML(data, cache.htmlView, false);\n            cache.htmlChart.resize();\n        };\n    }\n\n    // // update data\n    // option.color = [data.a('lineColor1'), data.a('lineColor2')];\n    // option.legend.data = [data.a('legendData1'), data.a('legendData2')];\n    option.series[0].data = data.a('barData');\n    option.series[0].itemStyle = {\n        normal: {\n            color: new echarts.graphic.LinearGradient(\n                0, 0, 1, 1,\n                [\n                    {offset: 0, color: data.a('color2')},\n                    {offset: 1, color: data.a('color1')}\n                ]\n            )\n        }\n    };\n    cache.htmlChart.setOption(option);\n\n    // html for showing\n    return cache.htmlView;\n}",
  "width": 200,
  "height": 120,
  "fitSize": true,
  "pixelPerfect": false,
  "attachStyle": "close",
  "comps": [
    {
      "type": "roundRect",
      "background": {
        "func": "attr@chartBackground",
        "value": "#030C20"
      },
      "borderColor": "#979797",
      "cornerRadius": 4,
      "visible": false,
      "rect": [
        0,
        0,
        200,
        120
      ]
    }
  ]
}