{
  "width": 13,
  "height": 58,
  "comps": [
    {
      "type": "shape",
      "borderWidth": 1,
      "borderColor": "#979797",
      "points": [
        6.59197,
        0.65557,
        6.72081,
        57.73152
      ]
    },
    {
      "type": "shape",
      "borderWidth": 1,
      "borderColor": {
        "func": "attr@b.color",
        "value": "rgb(212,0,0)"
      },
      "points": [
        0.63616,
        14.51604,
        6.49645,
        11.5859,
        12.64743,
        14.51604
      ]
    },
    {
      "type": "shape",
      "borderWidth": 1,
      "borderColor": {
        "func": "attr@b.color",
        "value": "rgb(212,0,0)"
      },
      "points": [
        0.74026,
        16.68157,
        6.60054,
        13.75143,
        12.75153,
        16.68157
      ]
    },
    {
      "type": "rect",
      "background": {
        "func": "attr@b.color",
        "value": "rgb(212,0,0)"
      },
      "borderWidth": 1,
      "borderColor": {
        "func": "attr@b.color",
        "value": "rgb(212,0,0)"
      },
      "rect": [
        2.2272,
        17.55255,
        8.64774,
        12.27044
      ]
    },
    {
      "type": "shape",
      "background": "#979797",
      "borderWidth": 1,
      "borderColor": "#979797",
      "closePath": true,
      "points": [
        2.2272,
        43.61263,
        6.66793,
        49.22197,
        10.79845,
        43.61263
      ]
    },
    {
      "type": "shape",
      "borderWidth": 1,
      "borderColor": {
        "func": "attr@b.color",
        "value": "rgb(212,0,0)"
      },
      "scaleY": -1,
      "points": [
        0.68821,
        35.88701,
        6.5485,
        32.95687,
        12.69948,
        35.88701
      ]
    },
    {
      "type": "shape",
      "borderWidth": 1,
      "borderColor": {
        "func": "attr@b.color",
        "value": "rgb(212,0,0)"
      },
      "scaleY": -1,
      "points": [
        0.79231,
        38.05254,
        6.65259,
        35.1224,
        12.80358,
        38.05254
      ]
    }
  ]
}